[
  {
    "url": "version.sass",
    "disabled": true,
    "checked": true,
    "title": "Информация о версии"
  },
  {
    "url": "copyright.sass",
    "disabled": true,
    "checked": true,
    "title": "Информация о теме"
  },
  {
    "url": "auto-scheme.sass",
    "checked": true,
    "title": "Автоподбор цветов схемы",
    "description": "ВАЖНО! Выключите этот файл, если хотите сами настраивать цвета схемы."
  },
  {
    "url": "css-variables.sass",
    "checked": true
  },
  {
    "url": "main.sass",
    "checked": true
  },
  {
    "url": "color.sass",
    "checked": true
  },
  {
    "url": "font-arial.sass",
    "cat": "font",
    "checked": false
  },
  {
    "url": "font-roboto.sass",
    "cat": "font",
    "checked": true
  },
  {
    "url": "font-roboto_condensed.sass",
    "cat": "font",
    "checked": false
  },
  {
    "url": "modules/material-icons.sass",
    "disabled": true,
    "checked": true
  },
  {
    "url": "modules/md-button.sass",
    "disabled": true,
    "checked": true
  },
  {
    "url": "modules/md-icon.sass",
    "disabled": true,
    "checked": true
  },
  {
    "url": "modules/md-scrollbar.sass",
    "disabled": true,
    "checked": true
  },
  {
    "url": "modules/md-tooltip.sass",
    "disabled": true,
    "checked": true
  },
  {
    "url": "modules/shiki-entry.sass",
    "checked": true
  },
  {
    "url": "modules/shiki-comment.sass",
    "checked": true
  },
  {
    "url": "modules/shiki-marker.sass",
    "checked": true
  },
  {
    "url": "modules/shiki-plashka.sass",
    "checked": true
  },
  {
    "url": "layouts/l-menu.sass",
    "checked": true,
    "description": "Обновлённое верхнее меню."
  },
  {
    "url": "layouts/l-sidebar.sass",
    "checked": true,
    "description": "Боковое меню."
  },
  {
    "url": "blocks/lib-buttons.sass",
    "checked": true
  },
  {
    "url": "blocks/lib-collapse.sass",
    "checked": true
  },
  {
    "url": "blocks/lib-columns.sass",
    "checked": true
  },
  {
    "url": "blocks/lib-headlines.sass",
    "checked": true
  },
  {
    "url": "blocks/lib-highcharts.sass",
    "checked": true
  },
  {
    "url": "blocks/lib-icons.sass",
    "checked": true
  },
  {
    "url": "blocks/lib-tipsy.sass",
    "checked": true
  },
  {
    "url": "blocks/lib-toastr.sass",
    "checked": true
  },
  {
    "url": "blocks/lib-tooltip.sass",
    "checked": true
  },
  {
    "url": "blocks/mixin-log_entry.sass",
    "checked": true
  },
  {
    "url": "blocks/b-achievement.sass",
    "checked": true
  },
  {
    "url": "blocks/b-achievements_notifier.sass",
    "checked": true,
    "description": "Строгие тёмные уведомления вместо цветных."
  },
  {
    "url": "blocks/b-add_to_list.sass",
    "checked": true
  },
  {
    "url": "blocks/b-ajax.sass",
    "checked": true
  },
  {
    "url": "blocks/b-anime_status_tag.sass",
    "checked": true
  },
  {
    "url": "blocks/b-badge.sass",
    "checked": true
  },
  {
    "url": "blocks/b-bb_codes-examples.sass",
    "checked": true
  },
  {
    "url": "blocks/b-block_list.sass",
    "checked": true
  },
  {
    "url": "blocks/b-breadcrumbs.sass",
    "checked": true
  },
  {
    "url": "blocks/b-buttons.sass",
    "checked": true
  },
  {
    "url": "blocks/b-catalog_entry.sass",
    "checked": true
  },
  {
    "url": "blocks/b-catalog_entry-tooltip.sass",
    "checked": true
  },
  {
    "url": "blocks/b-club.sass",
    "checked": true
  },
  {
    "url": "blocks/b-code.sass",
    "checked": true
  },
  {
    "url": "blocks/b-collection-filters.sass",
    "checked": true
  },
  {
    "url": "blocks/b-collection-topic.sass",
    "checked": true
  },
  {
    "url": "blocks/b-collection_item.sass",
    "checked": true
  },
  {
    "url": "blocks/b-collection_search.sass",
    "checked": true
  },
  {
    "url": "blocks/b-comment.sass",
    "checked": true
  },
  {
    "url": "blocks/b-comments.sass",
    "checked": true
  },
  {
    "url": "blocks/b-comments-notifier.sass",
    "checked": true
  },
  {
    "url": "blocks/b-coub.sass",
    "checked": true
  },
  {
    "url": "blocks/b-db_entry.sass",
    "checked": true
  },
  {
    "url": "blocks/b-db_entry-note.sass",
    "checked": true,
    "description": "«Связанное» и «Авторы» на страницах энциклопедии."
  },
  {
    "url": "blocks/b-dialog.sass",
    "checked": true
  },
  {
    "url": "blocks/b-dropzone.sass",
    "checked": true
  },
  {
    "url": "blocks/b-entry-info.sass",
    "checked": true
  },
  {
    "url": "blocks/b-feedback.sass",
    "checked": true
  },
  {
    "url": "blocks/b-footer_vote.sass",
    "checked": true
  },
  {
    "url": "blocks/b-form.sass",
    "checked": true
  },
  {
    "url": "blocks/b-forum.sass",
    "checked": true
  },
  {
    "url": "blocks/b-forums.sass",
    "checked": true
  },
  {
    "url": "blocks/b-gallery.sass",
    "checked": true
  },
  {
    "url": "blocks/b-height_shortener.sass",
    "checked": true
  },
  {
    "url": "blocks/b-hot_topics-v2.sass",
    "checked": true
  },
  {
    "url": "blocks/b-image.sass",
    "checked": true
  },
  {
    "url": "blocks/b-input.sass",
    "checked": true
  },
  {
    "url": "blocks/b-lang_trigger.sass",
    "checked": true
  },
  {
    "url": "blocks/b-link_button.sass",
    "checked": true
  },
  {
    "url": "blocks/b-list.sass",
    "checked": true
  },
  {
    "url": "blocks/b-list_switchers.sass",
    "checked": true
  },
  {
    "url": "blocks/b-message.sass",
    "checked": true
  },
  {
    "url": "blocks/b-modal.sass",
    "checked": true
  },
  {
    "url": "blocks/b-news_line-topic.sass",
    "checked": true
  },
  {
    "url": "blocks/b-news_wall-topic.sass",
    "checked": true
  },
  {
    "url": "blocks/b-oauth_application.sass",
    "checked": true
  },
  {
    "url": "blocks/b-options_floated.sass",
    "checked": true
  },
  {
    "url": "blocks/b-poll.sass",
    "checked": true
  },
  {
    "url": "blocks/b-quote.sass",
    "checked": true
  },
  {
    "url": "blocks/b-quote-v2.sass",
    "checked": true
  },
  {
    "url": "blocks/b-rate.sass",
    "checked": true
  },
  {
    "url": "blocks/b-review-topic.sass",
    "checked": true
  },
  {
    "url": "blocks/b-review_opinion_marker.sass",
    "checked": true
  },
  {
    "url": "blocks/b-reviews_navigation.sass",
    "checked": true
  },
  {
    "url": "blocks/b-critique_votes.sass",
    "checked": true
  },
  {
    "url": "blocks/b-shiki_editor.sass",
    "checked": true
  },
  {
    "url": "blocks/b-shiki_marker.sass",
    "checked": true
  },
  {
    "url": "blocks/b-source.sass",
    "checked": true
  },
  {
    "url": "blocks/b-spoiler.sass",
    "checked": true
  },
  {
    "url": "blocks/b-spoiler_block.sass",
    "checked": true
  },
  {
    "url": "blocks/b-spoiler_inline.sass",
    "checked": true
  },
  {
    "url": "blocks/b-stats_bar.sass",
    "checked": true
  },
  {
    "url": "blocks/b-status-line.sass",
    "checked": true
  },
  {
    "url": "blocks/b-subposter-actions.sass",
    "checked": true
  },
  {
    "url": "blocks/b-table.sass",
    "checked": true
  },
  {
    "url": "blocks/b-tag.sass",
    "checked": true
  },
  {
    "url": "blocks/b-to_top.sass",
    "checked": true
  },
  {
    "url": "blocks/b-topic.sass",
    "checked": true
  },
  {
    "url": "blocks/b-topic-preview.sass",
    "checked": true
  },
  {
    "url": "blocks/b-upload_progress.sass",
    "checked": true
  },
  {
    "url": "blocks/b-user.sass",
    "checked": true
  },
  {
    "url": "blocks/b-user16.sass",
    "checked": true
  },
  {
    "url": "blocks/b-user_rate.sass",
    "checked": true
  },
  {
    "url": "blocks/b-user_rate-history.sass",
    "checked": true
  },
  {
    "url": "blocks/b-video.sass",
    "checked": true,
    "description": "Изменённыё вид превью видео."
  },
  {
    "url": "blocks/td-icons.sass",
    "checked": true,
    "description": "Добавление к кнопкам иконок с помощью data-icon."
  },
  {
    "url": "blocks/td-tabs.sass",
    "checked": true,
    "description": "Фирменные табы с --ripple и --vertical."
  },
  {
    "url": "blocks/ti-tags.sass",
    "checked": true
  },
  {
    "url": "pages/p-achievements.sass",
    "checked": true
  },
  {
    "url": "pages/p-animes.sass",
    "checked": true
  },
  {
    "url": "pages/p-animes_collection.sass",
    "checked": true
  },
  {
    "url": "pages/p-animes-edit_field.sass",
    "checked": true
  },
  {
    "url": "pages/p-club_pages.sass",
    "checked": true
  },
  {
    "url": "pages/p-clubs.sass",
    "checked": true
  },
  {
    "url": "pages/p-collections_show.sass",
    "checked": true
  },
  {
    "url": "pages/p-contests.sass",
    "checked": true
  },
  {
    "url": "pages/p-dashboards.sass",
    "checked": true
  },
  {
    "url": "pages/p-dialogs.sass",
    "checked": true
  },
  {
    "url": "pages/p-oauth_applications.sass",
    "checked": true
  },
  {
    "url": "pages/p-profiles.sass",
    "checked": true
  },
  {
    "url": "pages/p-profiles--b-options_floated.sass",
    "checked": true
  },
  {
    "url": "pages/p-messages.sass",
    "checked": true
  },
  {
    "url": "pages/p-profiles_edit.sass",
    "checked": true
  },
  {
    "url": "pages/p-profiles_favorites.sass",
    "checked": true
  },
  {
    "url": "pages/p-topics.sass",
    "checked": true
  },
  {
    "url": "pages/p-user_history.sass",
    "checked": true
  },
  {
    "url": "pages/p-user_rates.sass",
    "checked": true
  },
  {
    "url": "pages/p-userlist_comparer.sass",
    "checked": true
  },
  {
    "url": "pages/p-users.sass",
    "checked": true
  },
  {
    "url": "profile-history_animation.sass",
    "checked": false,
    "description": "Для тех, у кого не отображаются полосы аниме и манги в профиле."
  },
  {
    "url": "profile-cover.sass",
    "checked": true,
    "disabled": true,
    "description": "Этот файл зависит от настройки «Вид профиля»."
  },
  {
    "url": "avatar-round.sass",
    "checked": true,
    "title": "Круглые аватарки"
  },
  {
    "url": "tests/immersive-cover.sass",
    "checked": true,
    "description": "Обложка-фон с большим отступом от меню."
  },
  {
    "url": "tests/profile-update.1.sass",
    "checked": true,
    "description": "Отображение времени за аниме и мангой."
  },
  {
    "url": "tests/profile-update.1.1.sass",
    "checked": true,
    "description": "Маленький блок достижений."
  },
  {
    "url": "tests/md-textfields.sass",
    "checked": true,
    "description": "Более \"материальные\" поля ввода."
  },
  {
    "url": "user-settings.sass",
    "checked": true
  }
]
